[
    {
        "quote": "Bizde böyle",
        "author": "Emre Salur"
    },
    {
        "quote": "Adam olana çok bile",
        "author": "Emre Salur"
    },
    {
        "quote": "2009'un yanındaki 0 sildiniz kaldı mı 9. 2'nin yanındakini de sildiniz kaldı mı 2. Toplayın 11 yapar. 2009'un içerisindeki iki sıfırı da sildiniz. Ne kaldı 29. 11'le 29'u toplayın. Kırk yapar!",
        "author": "Devlet Bahçeli"
    },
    {
        "quote": "Belki bir atom olamadık ama biz de parçalandık...",
        "author": "Albert Einstein"
    },
    {
        "quote": "Sparta Prag’ı Sparta’da yeneceğiz!",
        "author": "Ümit Özat"
    },
    {
        "quote": "Ben yanlış bir şeyler söylüyorsam, insanlar beni yanlış anlamasın.",
        "author": "Emre Belezöoğlu"
    },
    {
        "quote": "Türk gazetelerindeki tek doğru şey tarihtir",
        "author": "Haim Revivo"
    },
    {
        "quote": "Dün dündür, bugün bugündür",
        "author": "Süleyman Demirel"
    },
    {
        "quote": "Bizde yanlış olmaz, olmuşsa da yanlışlıkla olmuştur",
        "author": "Mert Salur"
    },
    {
        "quote": "Biz sayın başbakan gibi sözünün arkasında duran adam değiliz!",
        "author": "Kemal Kılıçdaroğlu"
    },
    {
        "quote": "Bu meclisin yarısı hıyardır!.. Sözümü geri alıyorum. Bu meclisin yarısı hıyar değildir...",
        "author": "Osman Yüksel Serdengeçti"
    },
    {
        "quote":"Olcay’ı Messi’ye neden tercih ederim? Çünkü her şeyden önce Kayserili. Messi’nin nereli olduğunu bilmiyoruz.",
        "author": "Samet Aybaba"
    },
    {
        "quote":"Türkiye’ye yabancı teknik direktör getirmeyin. Ben Türkçe anlatamıyorum, onlar nasıl anlatacak.",
        "author": "Yılmaz Vural"
    },
    {
        "quote":"Bunca yıllık futbol hayatım boyunca şunu anladım ki, gol atmadan maç kazanılmıyor.",
        "author": "Hami Mandıralı"
    },
    {
        "quote":"Oğlan dayıya, kız halaya çeker",
        "author": "Charles Darwin"
    }

]